fluxvault/__init__.py
fluxvault/app_init.py
fluxvault/cli.py
fluxvault/constants.py
fluxvault/extensions.py
fluxvault/fluxagent.py
fluxvault/fluxapp.py
fluxvault/fluxkeeper.py
fluxvault/fluxkeeper_gui.py
fluxvault/fs.py
fluxvault/helpers.py
fluxvault/log.py
fluxvault/registrar.py
fluxvault-0.13.0.dist-info/LICENSE
fluxvault-0.13.0.dist-info/METADATA
fluxvault-0.13.0.dist-info/WHEEL
fluxvault-0.13.0.dist-info/entry_points.txt
fluxvault-0.13.0.dist-info/RECORD
